[
    {
        "name": "Lolita Lynn",
        "gender": "female",
        "address": "389 Neptune Avenue, Belfair, Iowa, 6116",
        "books": [
            {
                "title": "Fundamentals of Wavelets",
                "author": "Goswami, Jaideva",
                "height": "228"
            },
            {
                "title": "Complete Sherlock Holmes, The - Vol I",
                "author": "Doyle, Arthur Conan",
                "height": "176"
            },
            {
                "title": "Textbook of Economic Theory",
                "author": "Stonier, Alfred",
                "height": "242"
            },
            {
                "title": "Great Indian Novel, The",
                "author": "Tharoor, Shashi",
                "height": "198"
            },
            {
                "title": "History of Western Philosophy",
                "author": "Russell, Bertrand",
                "height": "213"
            },
            {
                "title": "Flashpoint",
                "author": "",
                "height": "265"
            },
            {
                "title": "20000 Leagues Under the Sea",
                "author": "Verne, Jules",
                "height": "190"
            },
            {
                "title": "Judge, The",
                "author": "",
                "height": "170"
            }
        ]
    },
    {
        "name": "Tonia Hurst",
        "gender": "female",
        "address": "917 Terrace Place, Urbana, Idaho, 684",
        "books": [
            {
                "title": "Data Smart",
                "author": "Foreman, John",
                "height": "235"
            },
            {
                "title": "Complete Sherlock Holmes, The - Vol II",
                "author": "Doyle, Arthur Conan",
                "height": "176"
            },
            {
                "title": "Econometric Analysis",
                "author": "Greene, W. H.",
                "height": "242"
            },
            {
                "title": "O Jerusalem!",
                "author": "Lapierre, Dominique",
                "height": "217"
            },
            {
                "title": "Selected Short Stories",
                "author": "",
                "height": "215"
            },
            {
                "title": "Batman Earth One",
                "author": "",
                "height": "265"
            },
            {
                "title": "Batatyachi Chal",
                "author": "Deshpande P L",
                "height": "200"
            },
            {
                "title": "Attorney, The",
                "author": "",
                "height": "170"
            }
        ]
    },
    {
        "name": "Brooks Bright",
        "gender": "male",
        "address": "901 Mermaid Avenue, Wyoming, Marshall Islands, 8506",
        "books": [
            {
                "title": "God Created the Integers",
                "author": "Hawking, Stephen",
                "height": "197"
            },
            {
                "title": "Wealth of Nations, The",
                "author": "Smith, Adam",
                "height": "175"
            },
            {
                "title": "Learning OpenCV",
                "author": "Bradsky, Gary",
                "height": "232"
            },
            {
                "title": "City of Joy, The",
                "author": "Lapierre, Dominique",
                "height": "177"
            },
            {
                "title": "Rationality & Freedom",
                "author": "Sen, Amartya",
                "height": "213"
            },
            {
                "title": "Crisis on Infinite Earths",
                "author": "",
                "height": "258"
            },
            {
                "title": "Hafasavnuk",
                "author": "Deshpande P L",
                "height": "211"
            },
            {
                "title": "Prince, The",
                "author": "Machiavelli",
                "height": "173"
            }
        ]
    },
    {
        "name": "Kathrine Sharp",
        "gender": "female",
        "address": "989 Huron Street, Talpa, Utah, 7018",
        "books": [
            {
                "title": "Superfreakonomics",
                "author": "Dubner, Stephen",
                "height": "179"
            },
            {
                "title": "Pillars of the Earth, The",
                "author": "Follett, Ken",
                "height": "176"
            },
            {
                "title": "Data Structures Using C & C++",
                "author": "Tanenbaum, Andrew",
                "height": "235"
            },
            {
                "title": "Freedom at Midnight",
                "author": "Lapierre, Dominique",
                "height": "167"
            },
            {
                "title": "Clash of Civilizations and Remaking of the World Order",
                "author": "Huntington, Samuel",
                "height": "228"
            },
            {
                "title": "Numbers Behind Numb3rs, The",
                "author": "Devlin, Keith",
                "height": "202"
            },
            {
                "title": "Urlasurla",
                "author": "Deshpande P L",
                "height": "211"
            },
            {
                "title": "Eyeless in Gaza",
                "author": "Huxley, Aldous",
                "height": "180"
            }
        ]
    },
    {
        "name": "Shawn Harrell",
        "gender": "female",
        "address": "534 Hinsdale Street, Albany, Palau, 3291",
        "books": [
            {
                "title": "Orientalism",
                "author": "Said, Edward",
                "height": "197"
            },
            {
                "title": "Mein Kampf",
                "author": "Hitler, Adolf",
                "height": "212"
            },
            {
                "title": "Computer Vision, A Modern Approach",
                "author": "Forsyth, David",
                "height": "255"
            },
            {
                "title": "Winter of Our Discontent, The",
                "author": "Steinbeck, John",
                "height": "196"
            },
            {
                "title": "Uncommon Wisdom",
                "author": "Capra, Fritjof",
                "height": "197"
            },
            {
                "title": "Superman Earth One - 1",
                "author": "",
                "height": "259"
            },
            {
                "title": "Pointers in C",
                "author": "Kanetkar, Yashwant",
                "height": "213"
            },
            {
                "title": "Tales of Beedle the Bard",
                "author": "Rowling, J K",
                "height": "184"
            }
        ]
    },
    {
        "name": "Amy Casey",
        "gender": "female",
        "address": "589 Townsend Street, Hiseville, Connecticut, 7082",
        "books": [
            {
                "title": "Nature of Statistical Learning Theory, The",
                "author": "Vapnik, Vladimir",
                "height": "230"
            },
            {
                "title": "Tao of Physics, The",
                "author": "Capra, Fritjof",
                "height": "179"
            },
            {
                "title": "Principles of Communication Systems",
                "author": "Taub, Schilling",
                "height": "240"
            },
            {
                "title": "On Education",
                "author": "Russell, Bertrand",
                "height": "203"
            },
            {
                "title": "One",
                "author": "Bach, Richard",
                "height": "172"
            },
            {
                "title": "Superman Earth One - 2",
                "author": "",
                "height": "258"
            },
            {
                "title": "Cathedral and the Bazaar, The",
                "author": "Raymond, Eric",
                "height": "217"
            },
            {
                "title": "Girl with the Dragon Tattoo",
                "author": "Larsson, Steig",
                "height": "179"
            }
        ]
    },
    {
        "name": "Lorena Mejia",
        "gender": "female",
        "address": "614 High Street, Blanford, Maryland, 2776",
        "books": [
            {
                "title": "Integration of the Indian States",
                "author": "Menon, V P",
                "height": "217"
            },
            {
                "title": "Surely You're Joking Mr Feynman",
                "author": "Feynman, Richard",
                "height": "198"
            },
            {
                "title": "Let Us C",
                "author": "Kanetkar, Yashwant",
                "height": "213"
            },
            {
                "title": "Free Will",
                "author": "Harris, Sam",
                "height": "203"
            },
            {
                "title": "Karl Marx Biography",
                "author": "",
                "height": "162"
            },
            {
                "title": "Justice League: Throne of Atlantis",
                "author": "",
                "height": "258"
            },
            {
                "title": "Design with OpAmps",
                "author": "Franco, Sergio",
                "height": "240"
            },
            {
                "title": "Girl who kicked the Hornet's Nest",
                "author": "Larsson, Steig",
                "height": "179"
            }
        ]
    },
    {
        "name": "Allyson Wilkins",
        "gender": "female",
        "address": "572 Downing Street, Ivanhoe, American Samoa, 8235",
        "books": [
            {
                "title": "Drunkard's Walk, The",
                "author": "Mlodinow, Leonard",
                "height": "197"
            },
            {
                "title": "Farewell to Arms, A",
                "author": "Hemingway, Ernest",
                "height": "179"
            },
            {
                "title": "Amulet of Samarkand, The",
                "author": "Stroud, Jonathan",
                "height": "179"
            },
            {
                "title": "Bookless in Baghdad",
                "author": "Tharoor, Shashi",
                "height": "206"
            },
            {
                "title": "To Sir With Love",
                "author": "Braithwaite",
                "height": "197"
            },
            {
                "title": "Justice League: The Villain's Journey",
                "author": "",
                "height": "258"
            },
            {
                "title": "Think Complexity",
                "author": "Downey, Allen",
                "height": "230"
            },
            {
                "title": "Girl who played with Fire",
                "author": "Larsson, Steig",
                "height": "179"
            }
        ]
    },
    {
        "name": "Mays Reed",
        "gender": "male",
        "address": "306 Georgia Avenue, Hall, New Mexico, 1402",
        "books": [
            {
                "title": "Image Processing & Mathematical Morphology",
                "author": "Shih, Frank",
                "height": "241"
            },
            {
                "title": "Veteran, The",
                "author": "Forsyth, Frederick",
                "height": "177"
            },
            {
                "title": "Crime and Punishment",
                "author": "Dostoevsky, Fyodor",
                "height": "180"
            },
            {
                "title": "Case of the Lame Canary, The",
                "author": "Gardner, Earle Stanley",
                "height": "179"
            },
            {
                "title": "Half A Life",
                "author": "Naipaul, V S",
                "height": "196"
            },
            {
                "title": "Death of Superman, The",
                "author": "",
                "height": "258"
            },
            {
                "title": "Devil's Advocate, The",
                "author": "West, Morris",
                "height": "178"
            },
            {
                "title": "Batman Handbook",
                "author": "",
                "height": "270"
            }
        ]
    },
    {
        "name": "Katherine Mayer",
        "gender": "female",
        "address": "640 Prescott Place, Curtice, Kansas, 3395",
        "books": [
            {
                "title": "How to Think Like Sherlock Holmes",
                "author": "Konnikova, Maria",
                "height": "240"
            },
            {
                "title": "False Impressions",
                "author": "Archer, Jeffery",
                "height": "177"
            },
            {
                "title": "Angels & Demons",
                "author": "Brown, Dan",
                "height": "178"
            },
            {
                "title": "Theory of Everything, The",
                "author": "Hawking, Stephen",
                "height": "217"
            },
            {
                "title": "Discovery of India, The",
                "author": "Nehru, Jawaharlal",
                "height": "230"
            },
            {
                "title": "History of the DC Universe",
                "author": "",
                "height": "258"
            },
            {
                "title": "Ayn Rand Answers",
                "author": "Rand, Ayn",
                "height": "203"
            },
            {
                "title": "Murphy's Law",
                "author": "",
                "height": "178"
            }
        ]
    },
    {
        "name": "Kelly Byers",
        "gender": "female",
        "address": "865 Revere Place, Homeland, Arizona, 232",
        "books": [
            {
                "title": "Data Scientists at Work",
                "author": "Sebastian Gutierrez",
                "height": "230"
            },
            {
                "title": "Last Lecture, The",
                "author": "Pausch, Randy",
                "height": "197"
            },
            {
                "title": "Argumentative Indian, The",
                "author": "Sen, Amartya",
                "height": "209"
            },
            {
                "title": "New Markets & Other Essays",
                "author": "Drucker, Peter",
                "height": "176"
            },
            {
                "title": "Apulki",
                "author": "Deshpande, P L",
                "height": "211"
            },
            {
                "title": "Batman: The Long Halloween",
                "author": "",
                "height": "258"
            },
            {
                "title": "Philosophy: Who Needs It",
                "author": "Rand, Ayn",
                "height": "171"
            },
            {
                "title": "Structure and Randomness",
                "author": "Tao, Terence",
                "height": "252"
            }
        ]
    },
    {
        "name": "Schwartz Carey",
        "gender": "male",
        "address": "860 Centre Street, Hiwasse, Nevada, 2819",
        "books": [
            {
                "title": "Slaughterhouse Five",
                "author": "Vonnegut, Kurt",
                "height": "198"
            },
            {
                "title": "Return of the Primitive",
                "author": "Rand, Ayn",
                "height": "202"
            },
            {
                "title": "Sea of Poppies",
                "author": "Ghosh, Amitav",
                "height": "197"
            },
            {
                "title": "Electric Universe",
                "author": "Bodanis, David",
                "height": "201"
            },
            {
                "title": "Unpopular Essays",
                "author": "Russell, Bertrand",
                "height": "198"
            },
            {
                "title": "Life in Letters, A",
                "author": "Steinbeck, John",
                "height": "196"
            },
            {
                "title": "World's Great Thinkers, The",
                "author": "",
                "height": "189"
            },
            {
                "title": "Image Processing with MATLAB",
                "author": "Eddins, Steve",
                "height": "241"
            }
        ]
    },
    {
        "name": "Kay Beasley",
        "gender": "female",
        "address": "358 Sutton Street, Bellamy, Ohio, 8845",
        "books": [
            {
                "title": "Birth of a Theorem",
                "author": "Villani, Cedric",
                "height": "234"
            },
            {
                "title": "Jurassic Park",
                "author": "Crichton, Michael",
                "height": "174"
            },
            {
                "title": "Idea of Justice, The",
                "author": "Sen, Amartya",
                "height": "212"
            },
            {
                "title": "Hunchback of Notre Dame, The",
                "author": "Hugo, Victor",
                "height": "175"
            },
            {
                "title": "Deceiver, The",
                "author": "Forsyth, Frederick",
                "height": "178"
            },
            {
                "title": "Information, The",
                "author": "Gleick, James",
                "height": "233"
            },
            {
                "title": "Data Analysis with Open Source Tools",
                "author": "Janert, Phillip",
                "height": "230"
            },
            {
                "title": "Animal Farm",
                "author": "Orwell, George",
                "height": "180"
            }
        ]
    },
    {
        "name": "Robbins Gordon",
        "gender": "male",
        "address": "610 Langham Street, Boykin, Guam, 6688",
        "books": [
            {
                "title": "Structure & Interpretation of Computer Programs",
                "author": "Sussman, Gerald",
                "height": "240"
            },
            {
                "title": "Russian Journal, A",
                "author": "Steinbeck, John",
                "height": "196"
            },
            {
                "title": "Raisin in the Sun, A",
                "author": "Hansberry, Lorraine",
                "height": "175"
            },
            {
                "title": "Burning Bright",
                "author": "Steinbeck, John",
                "height": "175"
            },
            {
                "title": "Veil: Secret Wars of the CIA",
                "author": "Woodward, Bob",
                "height": "171"
            },
            {
                "title": "Journal of Economics, vol 106 No 3",
                "author": "",
                "height": "235"
            },
            {
                "title": "Broca's Brain",
                "author": "Sagan, Carl",
                "height": "174"
            },
            {
                "title": "Idiot, The",
                "author": "Dostoevsky, Fyodor",
                "height": "197"
            }
        ]
    },
    {
        "name": "Hillary Bauer",
        "gender": "female",
        "address": "951 Cumberland Street, Alleghenyville, Oregon, 7073",
        "books": [
            {
                "title": "Age of Wrath, The",
                "author": "Eraly, Abraham",
                "height": "238"
            },
            {
                "title": "Tales of Mystery and Imagination",
                "author": "Poe, Edgar Allen",
                "height": "172"
            },
            {
                "title": "All the President's Men",
                "author": "Woodward, Bob",
                "height": "177"
            },
            {
                "title": "Age of Discontuinity, The",
                "author": "Drucker, Peter",
                "height": "178"
            },
            {
                "title": "Char Shabda",
                "author": "Deshpande, P L",
                "height": "214"
            },
            {
                "title": "Elements of Information Theory",
                "author": "Thomas, Joy",
                "height": "229"
            },
            {
                "title": "Men of Mathematics",
                "author": "Bell, E T",
                "height": "217"
            },
            {
                "title": "Christmas Carol, A",
                "author": "Dickens, Charles",
                "height": "196"
            }
        ]
    },
    {
        "name": "Ruiz Phelps",
        "gender": "male",
        "address": "836 Troutman Street, Harborton, Kentucky, 4030",
        "books": [
            {
                "title": "Trial, The",
                "author": "Kafka, Frank",
                "height": "198"
            },
            {
                "title": "Freakonomics",
                "author": "Dubner, Stephen",
                "height": "197"
            },
            {
                "title": "Prisoner of Birth, A",
                "author": "Archer, Jeffery",
                "height": "176"
            },
            {
                "title": "Doctor in the Nude",
                "author": "Gordon, Richard",
                "height": "179"
            },
            {
                "title": "Rosy is My Relative",
                "author": "Durrell, Gerald",
                "height": "176"
            },
            {
                "title": "Power Electronics - Rashid",
                "author": "Rashid, Muhammad",
                "height": "235"
            },
            {
                "title": "Oxford book of Modern Science Writing",
                "author": "Dawkins, Richard",
                "height": "240"
            }
        ]
    },
    {
        "name": "Carolina Bryant",
        "gender": "female",
        "address": "377 Middagh Street, Ellerslie, Nebraska, 2644",
        "books": [
            {
                "title": "Statistical Decision Theory'",
                "author": "Pratt, John",
                "height": "236"
            },
            {
                "title": "Hidden Connections, The",
                "author": "Capra, Fritjof",
                "height": "197"
            },
            {
                "title": "Scoop!",
                "author": "Nayar, Kuldip",
                "height": "216"
            },
            {
                "title": "Down and Out in Paris & London",
                "author": "Orwell, George",
                "height": "179"
            },
            {
                "title": "Moon and Sixpence, The",
                "author": "Maugham, William S",
                "height": "180"
            },
            {
                "title": "Power Electronics - Mohan",
                "author": "Mohan, Ned",
                "height": "237"
            },
            {
                "title": "Justice, Judiciary and Democracy",
                "author": "Ranjan, Sudhanshu",
                "height": "224"
            }
        ]
    },
    {
        "name": "Sosa Lee",
        "gender": "male",
        "address": "364 Holly Street, Omar, California, 5140",
        "books": [
            {
                "title": "Data Mining Handbook",
                "author": "Nisbet, Robert",
                "height": "242"
            },
            {
                "title": "Story of Philosophy, The",
                "author": "Durant, Will",
                "height": "170"
            },
            {
                "title": "Ahe Manohar Tari",
                "author": "Deshpande, Sunita",
                "height": "213"
            },
            {
                "title": "Identity & Violence",
                "author": "Sen, Amartya",
                "height": "219"
            },
            {
                "title": "Political Philosophers",
                "author": "",
                "height": "162"
            },
            {
                "title": "Neural Networks",
                "author": "Haykin, Simon",
                "height": "240"
            },
            {
                "title": "Arthashastra, The",
                "author": "Kautiyla",
                "height": "214"
            }
        ]
    },
    {
        "name": "Lorna Scott",
        "gender": "female",
        "address": "878 Marconi Place, Gerton, Alabama, 845",
        "books": [
            {
                "title": "New Machiavelli, The",
                "author": "Wells, H. G.",
                "height": "180"
            },
            {
                "title": "Asami Asami",
                "author": "Deshpande, P L",
                "height": "205"
            },
            {
                "title": "Last Mughal, The",
                "author": "Dalrymple, William",
                "height": "199"
            },
            {
                "title": "Beyond the Three Seas",
                "author": "Dalrymple, William",
                "height": "197"
            },
            {
                "title": "Short History of the World, A",
                "author": "Wells, H G",
                "height": "197"
            },
            {
                "title": "Grapes of Wrath, The",
                "author": "Steinbeck, John",
                "height": "196"
            },
            {
                "title": "We the People",
                "author": "Palkhivala",
                "height": "216"
            }
        ]
    },
    {
        "name": "Bernard Holden",
        "gender": "male",
        "address": "674 Pine Street, Conestoga, Mississippi, 4727",
        "books": [
            {
                "title": "Physics & Philosophy",
                "author": "Heisenberg, Werner",
                "height": "197"
            },
            {
                "title": "Journal of a Novel",
                "author": "Steinbeck, John",
                "height": "196"
            },
            {
                "title": "Social Choice & Welfare, Vol 39 No. 1",
                "author": "Various",
                "height": "235"
            },
            {
                "title": "World's Greatest Short Stories, The",
                "author": "",
                "height": "217"
            },
            {
                "title": "Trembling of a Leaf, The",
                "author": "Maugham, William S",
                "height": "205"
            },
            {
                "title": "Vyakti ani Valli",
                "author": "Deshpande, P L",
                "height": "211"
            },
            {
                "title": "We the Nation",
                "author": "Palkhivala",
                "height": "216"
            }
        ]
    },
    {
        "name": "Craft Shields",
        "gender": "male",
        "address": "586 Java Street, Catherine, Arkansas, 1445",
        "books": [
            {
                "title": "Making Software",
                "author": "Oram, Andy",
                "height": "232"
            },
            {
                "title": "Once There Was a War",
                "author": "Steinbeck, John",
                "height": "196"
            },
            {
                "title": "Radiowaril Bhashane & Shrutika",
                "author": "Deshpande, P L",
                "height": "213"
            },
            {
                "title": "Talking Straight",
                "author": "Iacoca, Lee",
                "height": "175"
            },
            {
                "title": "Doctor on the Brain",
                "author": "Gordon, Richard",
                "height": "204"
            },
            {
                "title": "Statistical Learning Theory",
                "author": "Vapnik, Vladimir",
                "height": "228"
            },
            {
                "title": "Courtroom Genius, The",
                "author": "Sorabjee",
                "height": "217"
            }
        ]
    },
    {
        "name": "Mara English",
        "gender": "female",
        "address": "324 Herkimer Court, Boomer, Delaware, 5367",
        "books": [
            {
                "title": "Analysis, Vol I",
                "author": "Tao, Terence",
                "height": "248"
            },
            {
                "title": "Moon is Down, The",
                "author": "Steinbeck, John",
                "height": "196"
            },
            {
                "title": "Gun Gayin Awadi",
                "author": "Deshpande, P L",
                "height": "212"
            },
            {
                "title": "Maugham's Collected Short Stories, Vol 3",
                "author": "Maugham, William S",
                "height": "171"
            },
            {
                "title": "Simpsons & Their Mathematical Secrets",
                "author": "Singh, Simon",
                "height": "233"
            },
            {
                "title": "Empire of the Mughal - The Tainted Throne",
                "author": "Rutherford, Alex",
                "height": "180"
            },
            {
                "title": "Dongri to Dubai",
                "author": "Zaidi, Hussain",
                "height": "216"
            }
        ]
    },
    {
        "name": "Fisher Levy",
        "gender": "male",
        "address": "540 Adler Place, Hachita, Federated States Of Micronesia, 9894",
        "books": [
            {
                "title": "Machine Learning for Hackers",
                "author": "Conway, Drew",
                "height": "233"
            },
            {
                "title": "Brethren, The",
                "author": "Grisham, John",
                "height": "174"
            },
            {
                "title": "Aghal Paghal",
                "author": "Deshpande, P L",
                "height": "212"
            },
            {
                "title": "Phantom of Manhattan, The",
                "author": "Forsyth, Frederick",
                "height": "180"
            },
            {
                "title": "Pattern Classification",
                "author": "Duda, Hart",
                "height": "241"
            },
            {
                "title": "Empire of the Mughal - Brothers at War",
                "author": "Rutherford, Alex",
                "height": "180"
            },
            {
                "title": "History of England, Foundation",
                "author": "Ackroyd, Peter",
                "height": "197"
            }
        ]
    },
    {
        "name": "Cecelia Snyder",
        "gender": "female",
        "address": "236 Anchorage Place, Odessa, Michigan, 6314",
        "books": [
            {
                "title": "Signal and the Noise, The",
                "author": "Silver, Nate",
                "height": "233"
            },
            {
                "title": "In a Free State",
                "author": "Naipaul, V. S.",
                "height": "196"
            },
            {
                "title": "Maqta-e-Ghalib",
                "author": "Garg, Sanjay",
                "height": "221"
            },
            {
                "title": "Ashenden of The British Agent",
                "author": "Maugham, William S",
                "height": "160"
            },
            {
                "title": "From Beirut to Jerusalem",
                "author": "Friedman, Thomas",
                "height": "202"
            },
            {
                "title": "Empire of the Mughal - Ruler of the World",
                "author": "Rutherford, Alex",
                "height": "180"
            },
            {
                "title": "City of Djinns",
                "author": "Dalrymple, William",
                "height": "198"
            }
        ]
    },
    {
        "name": "Nina Kaufman",
        "gender": "female",
        "address": "538 Ashford Street, Boling, West Virginia, 7840",
        "books": [
            {
                "title": "Python for Data Analysis",
                "author": "McKinney, Wes",
                "height": "233"
            },
            {
                "title": "Catch 22",
                "author": "Heller, Joseph",
                "height": "178"
            },
            {
                "title": "Beyond Degrees",
                "author": "",
                "height": "222"
            },
            {
                "title": "Zen & The Art of Motorcycle Maintenance",
                "author": "Pirsig, Robert",
                "height": "172"
            },
            {
                "title": "Code Book, The",
                "author": "Singh, Simon",
                "height": "197"
            },
            {
                "title": "Empire of the Mughal - The Serpent's Tooth",
                "author": "Rutherford, Alex",
                "height": "180"
            },
            {
                "title": "India's Legal System",
                "author": "Nariman",
                "height": "177"
            }
        ]
    },
    {
        "name": "Dillard Branch",
        "gender": "male",
        "address": "225 Hampton Avenue, Bethany, Pennsylvania, 8056",
        "books": [
            {
                "title": "Introduction to Algorithms",
                "author": "Cormen, Thomas",
                "height": "234"
            },
            {
                "title": "Complete Mastermind, The",
                "author": "BBC",
                "height": "178"
            },
            {
                "title": "Manasa",
                "author": "Kale, V P",
                "height": "213"
            },
            {
                "title": "Great War for Civilization, The",
                "author": "Fisk, Robert",
                "height": "197"
            },
            {
                "title": "Age of the Warrior, The",
                "author": "Fisk, Robert",
                "height": "197"
            },
            {
                "title": "Empire of the Mughal - Raiders from the North",
                "author": "Rutherford, Alex",
                "height": "180"
            },
            {
                "title": "More Tears to Cry",
                "author": "Sassoon, Jean",
                "height": "235"
            }
        ]
    },
    {
        "name": "Dyer Bartlett",
        "gender": "male",
        "address": "880 Meadow Street, Seymour, Puerto Rico, 7921",
        "books": [
            {
                "title": "Beautiful and the Damned, The",
                "author": "Deb, Siddhartha",
                "height": "198"
            },
            {
                "title": "Dylan on Dylan",
                "author": "Dylan, Bob",
                "height": "197"
            },
            {
                "title": "India from Midnight to Milennium",
                "author": "Tharoor, Shashi",
                "height": "198"
            },
            {
                "title": "We the Living",
                "author": "Rand, Ayn",
                "height": "178"
            },
            {
                "title": "Final Crisis",
                "author": "",
                "height": "257"
            },
            {
                "title": "Mossad",
                "author": "Baz-Zohar, Michael",
                "height": "236"
            },
            {
                "title": "Ropemaker, The",
                "author": "Dickinson, Peter",
                "height": "196"
            }
        ]
    },
    {
        "name": "Tyler Dotson",
        "gender": "male",
        "address": "220 Herkimer Place, Turpin, Oklahoma, 4468",
        "books": [
            {
                "title": "Outsider, The",
                "author": "Camus, Albert",
                "height": "198"
            },
            {
                "title": "Soft Computing & Intelligent Systems",
                "author": "Gupta, Madan",
                "height": "242"
            },
            {
                "title": "World's Greatest Trials, The",
                "author": "",
                "height": "210"
            },
            {
                "title": "Artist and the Mathematician, The",
                "author": "Aczel, Amir",
                "height": "186"
            },
            {
                "title": "Killing Joke, The",
                "author": "",
                "height": "283"
            },
            {
                "title": "Jim Corbett Omnibus",
                "author": "Corbett, Jim",
                "height": "223"
            },
            {
                "title": "Angels & Demons",
                "author": "Brown, Dan",
                "height": "170"
            }
        ]
    }
]